bme280.py
bme281.py
micropython_bme280-1.2.dist-info/METADATA
micropython_bme280-1.2.dist-info/WHEEL
micropython_bme280-1.2.dist-info/top_level.txt
micropython_bme280-1.2.dist-info/RECORD
