Metadata-Version: 2.1
Name: micropython-bme280
Version: 1.2
Summary: bme280 module for MicroPython ESP8266/ESP32
Home-page: https://github.com/SebastianRoll/mpy_bme280_esp8266
Author: catdog2
Author-email: UNKNOWN
License: MIT
Platform: UNKNOWN
